{
  "file": "/home/mikhail/Correlations/ag123_u_rescaled.root",
  "save name": "Mf_W1.png",
  "axis title": {
    "X": "Centrality, (%)",
    "Y": ""
  },
  "axis range": {
    "min": -0.01,
    "max": 0.12
  },
  "correlations": [
    {
      "name": "M_RESCALED_W1_RECENTERED_Q1x_Q1x",
      "title": "(Mf,W1) XX",
      "rebin axis": [{"name": "mdc_vtx_tracks_rapidity", "n bins": 2, "low bin": 1.09, "up bin": 1.29}],
      "projection axis": "Centrality",
      "scale": 1.0,
      "color": "red",
      "marker": "full circle"
    },{
      "name": "M_RESCALED_W1_RECENTERED_Q1y_Q1y",
      "title": "(Mf,W1) YY",
      "rebin axis": [{"name": "mdc_vtx_tracks_rapidity", "n bins": 2, "low bin": 1.09, "up bin": 1.29}],
      "projection axis": "Centrality",
      "scale": 1.0,
      "color": "red",
      "marker": "open circle"
    },{
      "name": "M_RESCALED_W1_RECENTERED_Q1x_Q1y",
      "title": "(Mf,W1) XY",
      "rebin axis": [{"name": "mdc_vtx_tracks_rapidity", "n bins": 2, "low bin": 1.09, "up bin": 1.29}],
      "projection axis": "Centrality",
      "scale": 1.0,
      "color": "blue",
      "marker": "full square"
    },{
      "name": "M_RESCALED_W1_RECENTERED_Q1y_Q1x",
      "title": "(Mf,W1) YX",
      "rebin axis": [{"name": "mdc_vtx_tracks_rapidity", "n bins": 2, "low bin": 1.09, "up bin": 1.29}],
      "projection axis": "Centrality",
      "scale": 1.0,
      "color": "blue",
      "marker": "open square"
    }
  ]
}